Metadata-Version: 1.1
Name: itunescontroller
Version: 0.5
Summary: Play/Pause iTunes with face.
Home-page: https://github.com/v-adhithyan/itunes-controller
Author: Adhithyan Vijayakumar
Author-email: pollachi.developer@gmail.com
License: MIT
Keywords: itunes,control,hand,gestures
Platform: UNKNOWN
Classifier: Intended Audience :: End Users/Desktop
Classifier: Intended Audience :: Developers
Classifier: License :: OSI Approved :: MIT License
Classifier: Operating System :: MacOS
Classifier: Programming Language :: Python :: 2
Classifier: Programming Language :: Python :: 3
